pyrootutils/__init__.py
pyrootutils/pyrootutils.py
tests/__init__.py
tests/conftest.py
tests/test_pyrootutils.py
pyrootutils-1.0.4.dist-info/LICENSE
pyrootutils-1.0.4.dist-info/METADATA
pyrootutils-1.0.4.dist-info/WHEEL
pyrootutils-1.0.4.dist-info/top_level.txt
pyrootutils-1.0.4.dist-info/RECORD
