Metadata-Version: 2.1
Name: pyrootutils
Version: 1.0.4
Summary: Simple package for easy project root setup
Home-page: https://github.com/ashleve/pyrootutils
Author: ashleve
Author-email: ashlevegalaxy@gmail.com
License: MIT
Requires-Python: >=3.7.0
License-File: LICENSE
